sela_browse_sdk/__init__.py
sela_browse_sdk/__pycache__/__init__.cpython-312.pyc
sela_browse_sdk/__pycache__/sela.cpython-312.pyc
sela_browse_sdk/sela/__init__.py
sela_browse_sdk/sela/libsela_py.dylib
sela_browse_sdk/sela/sela.py
sela_browse_sdk/sela.py
sela_browse_sdk-1.0.2.dist-info/METADATA
sela_browse_sdk-1.0.2.dist-info/WHEEL
sela_browse_sdk-1.0.2.dist-info/RECORD
