Metadata-Version: 2.4
Name: sela-browse-sdk
Version: 1.0.2
Classifier: Development Status :: 3 - Alpha
Classifier: Intended Audience :: Developers
Classifier: License :: OSI Approved :: MIT License
Classifier: Programming Language :: Python :: 3
Classifier: Programming Language :: Python :: 3.9
Classifier: Programming Language :: Python :: 3.10
Classifier: Programming Language :: Python :: 3.11
Classifier: Programming Language :: Python :: 3.12
Classifier: Programming Language :: Rust
Classifier: Topic :: Internet :: WWW/HTTP :: Browsers
Classifier: Topic :: Software Development :: Libraries :: Python Modules
Summary: Sela Network Python SDK - P2P client for browser automation agents
Keywords: sela,p2p,libp2p,browser-automation,web-scraping,semantic
Author-email: Sela Network <dev@sela.network>
License: MIT
Requires-Python: >=3.9
Project-URL: documentation, https://github.com/sela-network/sela-node-v2/tree/main/client-sdk
Project-URL: homepage, https://github.com/sela-network/sela-node-v2
Project-URL: repository, https://github.com/sela-network/sela-node-v2
